benchmarks/__init__.py
tardis_em/__init__.py
tardis_em/_version.py
tardis_em/tardis.py
tardis_em/benchmarks/__init__.py
tardis_em/benchmarks/benchmarks.py
tardis_em/benchmarks/predictor.py
tardis_em/benchmarks/utils.py
tardis_em/cnn/__init__.py
tardis_em/cnn/cnn.py
tardis_em/cnn/train.py
tardis_em/cnn/trainer.py
tardis_em/cnn/data_processing/__init__.py
tardis_em/cnn/data_processing/draw_mask.py
tardis_em/cnn/data_processing/interpolation.py
tardis_em/cnn/data_processing/scaling.py
tardis_em/cnn/data_processing/stitch.py
tardis_em/cnn/data_processing/trim.py
tardis_em/cnn/datasets/__init__.py
tardis_em/cnn/datasets/augmentation.py
tardis_em/cnn/datasets/build_dataset.py
tardis_em/cnn/datasets/dataloader.py
tardis_em/cnn/model/__init__.py
tardis_em/cnn/model/convolution.py
tardis_em/cnn/model/decoder_blocks.py
tardis_em/cnn/model/encoder_blocks.py
tardis_em/cnn/model/init_weights.py
tardis_em/cnn/utils/__init__.py
tardis_em/cnn/utils/build_cnn.py
tardis_em/cnn/utils/utils.py
tardis_em/dist_pytorch/__init__.py
tardis_em/dist_pytorch/dist.py
tardis_em/dist_pytorch/sparse_dist.py
tardis_em/dist_pytorch/train.py
tardis_em/dist_pytorch/trainer.py
tardis_em/dist_pytorch/datasets/__init__.py
tardis_em/dist_pytorch/datasets/augmentation.py
tardis_em/dist_pytorch/datasets/dataloader.py
tardis_em/dist_pytorch/datasets/patches.py
tardis_em/dist_pytorch/model/__init__.py
tardis_em/dist_pytorch/model/embedding.py
tardis_em/dist_pytorch/model/layers.py
tardis_em/dist_pytorch/model/modules.py
tardis_em/dist_pytorch/sparse_model/__init__.py
tardis_em/dist_pytorch/sparse_model/embedding.py
tardis_em/dist_pytorch/sparse_model/layers.py
tardis_em/dist_pytorch/sparse_model/modules.py
tardis_em/dist_pytorch/utils/__init__.py
tardis_em/dist_pytorch/utils/build_point_cloud.py
tardis_em/dist_pytorch/utils/segment_point_cloud.py
tardis_em/dist_pytorch/utils/utils.py
tardis_em/scripts/__init__.py
tardis_em/scripts/compare_spatial_graphs.py
tardis_em/scripts/fetch_weights_file.py
tardis_em-0.3.22.dist-info/licenses/LICENSE
tardis_em-0.3.22.dist-info/METADATA
tardis_em-0.3.22.dist-info/WHEEL
tardis_em-0.3.22.dist-info/entry_points.txt
tardis_em-0.3.22.dist-info/top_level.txt
tardis_em-0.3.22.dist-info/RECORD
